globalmart_api/__init__.py
globalmart_api/oops.py
globalmart_api_tool-0.1.dist-info/METADATA
globalmart_api_tool-0.1.dist-info/WHEEL
globalmart_api_tool-0.1.dist-info/top_level.txt
globalmart_api_tool-0.1.dist-info/RECORD
