Metadata-Version: 2.1
Name: globalmart-api-tool
Version: 0.1
Summary: API package that provides the method to fetch data and convert to dataframe.
Author: Jayasree
Author-email: jayasreevaranasi4@gmail.com
License: MIT
Requires-Dist: pandas
Requires-Dist: requests
